nepali_translator/__init__.py
nepali_translator/translator.py
nepali_translator_package-0.1.0.dist-info/METADATA
nepali_translator_package-0.1.0.dist-info/WHEEL
nepali_translator_package-0.1.0.dist-info/top_level.txt
nepali_translator_package-0.1.0.dist-info/RECORD
